taskflow/__init__.py
taskflow/atom.py
taskflow/deciders.py
taskflow/exceptions.py
taskflow/flow.py
taskflow/formatters.py
taskflow/logging.py
taskflow/retry.py
taskflow/states.py
taskflow/storage.py
taskflow/task.py
taskflow/test.py
taskflow/version.py
taskflow/conductors/__init__.py
taskflow/conductors/base.py
taskflow/conductors/backends/__init__.py
taskflow/conductors/backends/impl_blocking.py
taskflow/conductors/backends/impl_executor.py
taskflow/conductors/backends/impl_nonblocking.py
taskflow/contrib/__init__.py
taskflow/engines/__init__.py
taskflow/engines/base.py
taskflow/engines/helpers.py
taskflow/engines/action_engine/__init__.py
taskflow/engines/action_engine/builder.py
taskflow/engines/action_engine/compiler.py
taskflow/engines/action_engine/completer.py
taskflow/engines/action_engine/deciders.py
taskflow/engines/action_engine/engine.py
taskflow/engines/action_engine/executor.py
taskflow/engines/action_engine/runtime.py
taskflow/engines/action_engine/scheduler.py
taskflow/engines/action_engine/scopes.py
taskflow/engines/action_engine/selector.py
taskflow/engines/action_engine/traversal.py
taskflow/engines/action_engine/actions/__init__.py
taskflow/engines/action_engine/actions/base.py
taskflow/engines/action_engine/actions/retry.py
taskflow/engines/action_engine/actions/task.py
taskflow/engines/worker_based/__init__.py
taskflow/engines/worker_based/dispatcher.py
taskflow/engines/worker_based/endpoint.py
taskflow/engines/worker_based/engine.py
taskflow/engines/worker_based/executor.py
taskflow/engines/worker_based/protocol.py
taskflow/engines/worker_based/proxy.py
taskflow/engines/worker_based/server.py
taskflow/engines/worker_based/types.py
taskflow/engines/worker_based/worker.py
taskflow/examples/99_bottles.py
taskflow/examples/alphabet_soup.py
taskflow/examples/build_a_car.py
taskflow/examples/buildsystem.py
taskflow/examples/calculate_in_parallel.py
taskflow/examples/calculate_linear.py
taskflow/examples/create_parallel_volume.py
taskflow-6.1.0.dist-info/licenses/AUTHORS
taskflow-6.1.0.dist-info/licenses/LICENSE
taskflow-6.1.0.dist-info/METADATA
taskflow-6.1.0.dist-info/WHEEL
taskflow-6.1.0.dist-info/entry_points.txt
taskflow-6.1.0.dist-info/pbr.json
taskflow-6.1.0.dist-info/top_level.txt
taskflow-6.1.0.dist-info/RECORD
