Metadata-Version: 2.4
Name: taskflow
Version: 6.1.0
Summary: Taskflow structured state management library.
Author-email: OpenStack <openstack-discuss@lists.openstack.org>
License: Apache-2.0
Project-URL: Homepage, https://docs.openstack.org/taskflow
Project-URL: Repository, https://opendev.org/openstack/taskflow
Classifier: Development Status :: 5 - Production/Stable
Classifier: Environment :: Console
Classifier: Intended Audience :: Developers
Classifier: License :: OSI Approved :: Apache Software License
Classifier: Operating System :: POSIX :: Linux
Classifier: Programming Language :: Python
Classifier: Programming Language :: Python :: 3
Classifier: Programming Language :: Python :: 3.10
Classifier: Programming Language :: Python :: 3.11
Classifier: Programming Language :: Python :: 3.12
Classifier: Programming Language :: Python :: 3.13
Classifier: Topic :: Software Development :: Libraries
Classifier: Topic :: System :: Distributed Computing
Requires-Python: >=3.10
License-File: LICENSE
License-File: AUTHORS
Requires-Dist: pbr>=2.0.0
Requires-Dist: debtcollector>=1.2.0
Requires-Dist: futurist>=1.2.0
Requires-Dist: fasteners>=0.17.3
Requires-Dist: networkx>=2.1.0
Requires-Dist: stevedore>=1.20.0
Requires-Dist: jsonschema>=3.2.0
Requires-Dist: automaton>=1.9.0
Requires-Dist: oslo.utils>=3.33.0
Requires-Dist: oslo.serialization>=2.18.0
Requires-Dist: tenacity>=6.0.0
Requires-Dist: cachetools>=2.0.0
Requires-Dist: pydot>=1.2.4
Provides-Extra: zookeeper
Requires-Dist: kazoo>=2.6.0; extra == "zookeeper"
Provides-Extra: redis
Requires-Dist: redis>=4.0.0; extra == "redis"
Provides-Extra: etcd
Requires-Dist: etcd3gw>=2.0.0; extra == "etcd"
Provides-Extra: workers
Requires-Dist: kombu>=4.3.0; extra == "workers"
Provides-Extra: eventlet
Requires-Dist: eventlet>=0.18.2; extra == "eventlet"
Provides-Extra: database
Requires-Dist: SQLAlchemy>=1.0.10; extra == "database"
Requires-Dist: alembic>=0.8.10; extra == "database"
Requires-Dist: SQLAlchemy-Utils>=0.30.11; extra == "database"
Requires-Dist: PyMySQL>=0.7.6; extra == "database"
Requires-Dist: psycopg2>=2.8.0; extra == "database"
Dynamic: license-file
Dynamic: requires-dist
